cligj/__init__.py
cligj/features.py
cligj-0.7.0.dist-info/LICENSE
cligj-0.7.0.dist-info/METADATA
cligj-0.7.0.dist-info/WHEEL
cligj-0.7.0.dist-info/top_level.txt
cligj-0.7.0.dist-info/RECORD
