Metadata-Version: 2.1
Name: cligj
Version: 0.7.0
Summary: Click params for commmand line interfaces to GeoJSON
Home-page: https://github.com/mapbox/cligj
Author: Sean Gillies
Author-email: sean@mapbox.com
License: BSD
Platform: UNKNOWN
Requires-Python: >=2.7, !=3.0.*, !=3.1.*, !=3.2.*, <4
Provides-Extra: test
